LICENSE
MANIFEST.in
README.rst
setup.py
asya/__init__.py
asya/__main__.py
asya/cli.py
asya/exceptions.py
asya/logic.py
asya/supervisor.py
asya.egg-info/PKG-INFO
asya.egg-info/SOURCES.txt
asya.egg-info/dependency_links.txt
asya.egg-info/entry_points.txt
asya.egg-info/requires.txt
asya.egg-info/top_level.txt
docs/Makefile
docs/api.rst
docs/cli.rst
docs/conf.py
docs/index.rst
docs/intro.rst
docs/make.bat
docs/requirements.txt