Metadata-Version: 1.2
Name: asya
Version: 0.1
Summary: Asynchronously your acquaintances from GitHub issues
Home-page: https://github.com/MarekSuchanek/asya
Author: Marek Suchánek
Author-email: suchama4@fit.cvut.cz
License: MIT
Keywords: github issues social search asyncio comments issues
Platform: UNKNOWN
Classifier: Development Status :: 1 - Planning
Classifier: Framework :: AsyncIO
Classifier: Intended Audience :: Developers
Classifier: Intended Audience :: Education
Classifier: Intended Audience :: Information Technology
Classifier: Intended Audience :: Science/Research
Classifier: License :: OSI Approved :: MIT License
Classifier: Natural Language :: English
Classifier: Programming Language :: Python
Classifier: Programming Language :: Python :: 3
Classifier: Programming Language :: Python :: 3.5
Classifier: Programming Language :: Python :: 3.6
Classifier: Topic :: Communications
Classifier: Topic :: Sociology
Requires-Python: >=3.4
